winlin.cpython-310-x86_64-linux-gnu.so
test.py
winlin-1.0.0.dist-info/RECORD
winlin-1.0.0.dist-info/METADATA
winlin-1.0.0.dist-info/entry_points.txt
winlin-1.0.0.dist-info/LICENSE
winlin-1.0.0.dist-info/WHEEL
winlin-1.0.0.dist-info/top_level.txt
winlin.libs/libXinerama-b7a62e01.so.1.0.0
winlin.libs/libxkbcommon-71ae2972.so.0.0.0
winlin.libs/libxdo-2dcbaab0.so.3
winlin.libs/libXi-e28fba09.so.6.1.0
winlin.libs/libXtst-70a8a00c.so.6.1.0
