Metadata-Version: 2.1
Name: winlin
Version: 1.0.0
Summary: Read the latest Real Python tutorials
Home-page: https://google.com
Author: Connor Johnson
Author-email: Connor James Johnson <conjamesnor@gmail.com>
License: GNU GENERAL PUBLIC LICENSE
Project-URL: Homepage, https://syntaxfiend.com/winlin
Keywords: x11,linux,ubuntu,kde,gnome,xdotool,windowmanager,wmctrl,C extensions
Classifier: License :: OSI Approved :: GNU General Public License v3 (GPLv3)
Classifier: Programming Language :: Python :: 3
Requires-Python: >=3.8
License-File: LICENSE
Provides-Extra: dev
